mcp_client_for_testing/__init__.py
mcp_client_for_testing/_version.py
mcp_client_for_testing/client.py
mcp_client_for_testing-0.1.8.dist-info/licenses/LICENSE
mcp_client_for_testing-0.1.8.dist-info/METADATA
mcp_client_for_testing-0.1.8.dist-info/WHEEL
mcp_client_for_testing-0.1.8.dist-info/entry_points.txt
mcp_client_for_testing-0.1.8.dist-info/top_level.txt
mcp_client_for_testing-0.1.8.dist-info/RECORD
