Metadata-Version: 2.4
Name: mcp-client-for-testing
Version: 0.1.8
Summary: A minimalistic MCP client for testing MCP Server
Author-email: Piet Brömmel <piet.broemmel@gmail.com>
License-Expression: MIT
Project-URL: Homepage, https://github.com/piebro/mcp-client-for-testing
Project-URL: Bug Tracker, https://github.com/piebro/mcp-client-for-testing/issues
Keywords: mcp,client,testing
Classifier: Development Status :: 4 - Beta
Classifier: Intended Audience :: Developers
Classifier: Programming Language :: Python :: 3
Classifier: Programming Language :: Python :: 3.10
Requires-Python: >=3.10
License-File: LICENSE
Requires-Dist: ruff
Requires-Dist: mcp
Dynamic: license-file
